shellgpt/__init__.py
shellgpt/__main__.py
shellgpt/app.py
shellgpt/history.py
shellgpt/api/llm.py
shellgpt/tui/app.py
shellgpt/utils/common.py
shellgpt/utils/conf.py
shellgpt/utils/http.py
shgpt-0.6.3.dist-info/METADATA
shgpt-0.6.3.dist-info/WHEEL
shgpt-0.6.3.dist-info/entry_points.txt
shgpt-0.6.3.dist-info/top_level.txt
shgpt-0.6.3.dist-info/RECORD
