Metadata-Version: 2.4
Name: shgpt
Version: 0.6.3
Summary: Chat with LLM in your terminal, be it shell generator, story teller, linux-terminal, etc.
Author-email: Jiacai Liu <dev@liujiacai.net>
License-Expression: GPL-3.0
Project-URL: Repository, https://github.com/jiacai2050/my-works/tree/main/shellgpt
Project-URL: Issues, https://github.com/jiacai2050/my-works/issues
Keywords: ai,llm,shell,gpt
Classifier: Operating System :: OS Independent
Classifier: Topic :: Software Development
Classifier: Topic :: Scientific/Engineering :: Artificial Intelligence
Classifier: Intended Audience :: Information Technology
Classifier: Intended Audience :: System Administrators
Classifier: Intended Audience :: Developers
Classifier: Programming Language :: Python :: 3
Classifier: Programming Language :: Python :: 3 :: Only
Classifier: Programming Language :: Python :: 3.6
Classifier: Programming Language :: Python :: 3.7
Classifier: Programming Language :: Python :: 3.8
Classifier: Programming Language :: Python :: 3.9
Classifier: Programming Language :: Python :: 3.10
Classifier: Programming Language :: Python :: 3.11
Requires-Python: >=3.0.0
Requires-Dist: requests
Requires-Dist: pyperclip
Provides-Extra: test
